flowshape/__init__.py
flowshape/dirac.py
flowshape/fit.py
flowshape/flow.py
flowshape/so3.py
flowshape/stat.py
flowshape/util.py
flowshape/icosphere/ico1.obj
flowshape/icosphere/ico2.obj
flowshape/icosphere/ico3.obj
flowshape/icosphere/ico4.obj
flowshape/icosphere/ico5.obj
flowshape/icosphere/ico6.obj
flowshape/lie_learn/LICENSE
flowshape/lie_learn/README.md
flowshape/lie_learn/__init__.py
flowshape/lie_learn/SO3/J_dense_0-150.npy
flowshape/lie_learn/SO3/SO3FFT.py
flowshape/lie_learn/SO3/__init__.py
flowshape/lie_learn/SO3/irrep_bases.py
flowshape/lie_learn/SO3/pinchon_hoggan_dense.py
flowshape/lie_learn/SO3/wigner_d.py
flowshape-0.1.5.dist-info/METADATA
flowshape-0.1.5.dist-info/WHEEL
flowshape-0.1.5.dist-info/licenses/LICENSE
flowshape-0.1.5.dist-info/RECORD
