Metadata-Version: 2.3
Name: flowshape
Version: 0.1.5
Summary: Cell shape analysis using the spherical harmonics decomposition
Project-URL: Paper, https://doi.org/10.1093/bioinformatics/btad383
Project-URL: Homepage, https://bitbucket.org/pgmsembryogenesis/flowshape/
Project-URL: Bug Tracker, https://bitbucket.org/pgmsembryogenesis/flowshape/issues
Author-email: Casper van Bavel <casper.vanbavel@kuleuven.be>
Classifier: License :: OSI Approved :: GNU General Public License v3 (GPLv3)
Classifier: Operating System :: OS Independent
Classifier: Programming Language :: Python :: 3
Requires-Python: >=3.7
Requires-Dist: libigl==2.5
Requires-Dist: numpy==1.26
